geckoterminal/__init__.py
geckoterminal/api.py
geckoterminal/client.py
geckoterminal/config.py
geckoterminal-0.0.6.dist-info/LICENSE
geckoterminal-0.0.6.dist-info/METADATA
geckoterminal-0.0.6.dist-info/WHEEL
geckoterminal-0.0.6.dist-info/top_level.txt
geckoterminal-0.0.6.dist-info/RECORD
