Metadata-Version: 2.1
Name: geckoterminal
Version: 0.0.6
Requires-Python: >=3.6
License-File: LICENSE
Requires-Dist: requests >=2.0.0
Requires-Dist: pandas >=2.0.0
